gardsdk/__init__.py
gardsdk/cdp_actions.py
gardsdk/cdp_creation.py
gardsdk/helpers.py
gardsdk-0.0.1.dist-info/LICENSE
gardsdk-0.0.1.dist-info/METADATA
gardsdk-0.0.1.dist-info/WHEEL
gardsdk-0.0.1.dist-info/top_level.txt
gardsdk-0.0.1.dist-info/RECORD
