Metadata-Version: 2.1
Name: gardsdk
Version: 0.0.1
Summary: Python software development kit for AlgoGard
Author: Alan Sikarov
Author-email: alan@algogard.com
Classifier: Programming Language :: Python :: 3
Classifier: License :: OSI Approved :: MIT License
License-File: LICENSE
